hope_flex_fields/__init__.py
hope_flex_fields/apps.py
hope_flex_fields/config.py
hope_flex_fields/exceptions.py
hope_flex_fields/fields.py
hope_flex_fields/file_handlers.py
hope_flex_fields/forms.py
hope_flex_fields/mixin.py
hope_flex_fields/registry.py
hope_flex_fields/types.pyi
hope_flex_fields/utils.py
hope_flex_fields/validators.py
hope_flex_fields/widgets.py
hope_flex_fields/xlsx.py
hope_flex_fields/__pycache__/__init__.cpython-312.pyc
hope_flex_fields/__pycache__/__init__.cpython-313.pyc
hope_flex_fields/__pycache__/apps.cpython-312.pyc
hope_flex_fields/__pycache__/apps.cpython-313.pyc
hope_flex_fields/__pycache__/config.cpython-312.pyc
hope_flex_fields/__pycache__/config.cpython-313.pyc
hope_flex_fields/__pycache__/exceptions.cpython-312.pyc
hope_flex_fields/__pycache__/exceptions.cpython-313.pyc
hope_flex_fields/__pycache__/fields.cpython-312.pyc
hope_flex_fields/__pycache__/fields.cpython-313.pyc
hope_flex_fields/__pycache__/file_handlers.cpython-312.pyc
hope_flex_fields/__pycache__/file_handlers.cpython-313.pyc
hope_flex_fields/__pycache__/forms.cpython-312.pyc
hope_flex_fields/__pycache__/forms.cpython-313.pyc
hope_flex_fields/__pycache__/mixin.cpython-312.pyc
hope_flex_fields/__pycache__/mixin.cpython-313.pyc
hope_flex_fields/__pycache__/registry.cpython-312.pyc
hope_flex_fields/__pycache__/registry.cpython-313.pyc
hope_flex_fields/__pycache__/utils.cpython-312.pyc
hope_flex_fields/__pycache__/utils.cpython-313.pyc
hope_flex_fields/__pycache__/validators.cpython-312.pyc
hope_flex_fields/__pycache__/validators.cpython-313.pyc
hope_flex_fields/__pycache__/widgets.cpython-312.pyc
hope_flex_fields/__pycache__/widgets.cpython-313.pyc
hope_flex_fields/__pycache__/xlsx.cpython-312.pyc
hope_flex_fields/__pycache__/xlsx.cpython-313.pyc
hope_flex_fields/admin/__init__.py
hope_flex_fields/admin/datachecker.py
hope_flex_fields/admin/definition.py
hope_flex_fields/admin/fieldset.py
hope_flex_fields/admin/flexfield.py
hope_flex_fields-0.7.5.dist-info/METADATA
hope_flex_fields-0.7.5.dist-info/WHEEL
hope_flex_fields-0.7.5.dist-info/top_level.txt
hope_flex_fields-0.7.5.dist-info/RECORD
