Metadata-Version: 2.4
Name: hope-flex-fields
Version: 0.7.5
Author-email: sax <s.apostolico@gmail.com>
License: MIT
Classifier: Programming Language :: Python :: 3 :: Only
Classifier: Programming Language :: Python :: 3.11
Classifier: Programming Language :: Python :: 3.12
Classifier: Programming Language :: Python :: 3.13
Requires-Python: >=3.11
Requires-Dist: deepdiff
Requires-Dist: deprecation
Requires-Dist: django-admin-extra-buttons
Requires-Dist: django-adminactions
Requires-Dist: django-jsoneditor
Requires-Dist: django-regex
Requires-Dist: django-regex-field
Requires-Dist: django-strategy-field
Requires-Dist: djangorestframework
Requires-Dist: jmespath
Requires-Dist: jsonpickle
Requires-Dist: mini-racer
Requires-Dist: python-calamine
Requires-Dist: requests
Requires-Dist: xlsxwriter
Provides-Extra: docs
Requires-Dist: mkdocs; extra == "docs"
Requires-Dist: mkdocs-awesome-pages-plugin; extra == "docs"
Requires-Dist: mkdocs-material; extra == "docs"
Requires-Dist: mkdocstrings-python; extra == "docs"
